{
  "appoiments": [
    {
      "id": "a7b5",
      "bname": "pratima kushwaha",
      "bemail": "pratimaku6267@gamil.com",
      "bphone": "06267334973",
      "baddress": "rewa",
      "bcity": "rewa",
      "bstate": "Madhya Pradesh",
      "bzip": "486226",
      "bcountry": "India",
      "bcheckin": "2025-11-07",
      "bcheckout": "2025-11-07",
      "bno": "3",
      "bgender": "Female",
      "badults": "2",
      "bkids": "0"
    },
    {
      "id": "65df",
      "bname": "pratima kushwaha",
      "bemail": "pratimaku6267@gamil.com",
      "bphone": "06267334973",
      "baddress": "rewa",
      "bcity": "rewa",
      "bstate": "Madhya Pradesh",
      "bzip": "486226",
      "bcountry": "India",
      "bcheckin": "2025-10-08",
      "bcheckout": "2025-10-16",
      "bno": "3",
      "bgender": "Male",
      "badults": "2",
      "bkids": "0"
    },
    {
      "id": "9888",
      "bname": "pratima kushwaha",
      "bemail": "pratimaku6267@gamil.com",
      "bphone": "06267334973",
      "baddress": "rewa",
      "bcity": "rewa",
      "bstate": "Madhya Pradesh",
      "bzip": "486226",
      "bcountry": "India",
      "bcheckin": "2025-10-08",
      "bcheckout": "2025-10-16",
      "bno": "3",
      "bgender": "Male",
      "badults": "2",
      "bkids": "0"
    },
    {
      "id": "bc54",
      "bname": "pratima kushwaha",
      "bemail": "pratimaku6267@gamil.com",
      "bphone": "06267334973",
      "baddress": "rewa",
      "bcity": "rewa",
      "bstate": "Madhya Pradesh",
      "bzip": "486226",
      "bcountry": "India",
      "bcheckin": "2025-10-08",
      "bcheckout": "2025-10-16",
      "bno": "3",
      "bgender": "Male",
      "badults": "2",
      "bkids": "0"
    },
    {
      "id": "d510",
      "bname": "pratima kushwaha",
      "bemail": "pratimaku6267@gamil.com",
      "bphone": "06267334973",
      "baddress": "rewa",
      "bcity": "rewa",
      "bstate": "Madhya Pradesh",
      "bzip": "486226",
      "bcountry": "India",
      "bcheckin": "2025-10-08",
      "bcheckout": "2025-10-16",
      "bno": "3",
      "bgender": "Male",
      "badults": "2",
      "bkids": "0"
    },
    {
      "id": "b6ee",
      "bname": "pratima kushwaha",
      "bemail": "pratimaku6267@gamil.com",
      "bphone": "06267334973",
      "baddress": "rewa",
      "bcity": "rewa",
      "bstate": "Madhya Pradesh",
      "bzip": "486226",
      "bcountry": "India",
      "bcheckin": "2025-10-08",
      "bcheckout": "2025-10-16",
      "bno": "3",
      "bgender": "Male",
      "badults": "2",
      "bkids": "0"
    },
    {
      "id": "8a80",
      "bname": "pratima kushwaha",
      "bemail": "pratimaku6267@gamil.com",
      "bphone": "06267334973",
      "baddress": "rewa",
      "bcity": "rewa",
      "bstate": "Madhya Pradesh",
      "bzip": "486226",
      "bcountry": "India",
      "bcheckin": "2025-10-08",
      "bcheckout": "2025-10-16",
      "bno": "2",
      "bgender": "Male",
      "badults": "2",
      "bkids": "0"
    }
  ]
}